{
  "obligation_id": "derive_beta_coefficient_from_first_principles",
  "script_id": "02_mechanics__candidate_orbit_space_action",
  "title": "Derive beta=16\u03c0G K_A/c\u00b2 from first principles",
  "status": "open",
  "required_by": [],
  "satisfied_by": [],
  "failed_by": [],
  "superseded_by": null,
  "created_at": "2026-05-10T17:18:11.764540+00:00",
  "description": "The coupling beta=16\u03c0G K_A/c\u00b2 is fixed by matching to the Poisson normalization. Its origin from a deeper variational or geometric principle is not derived.",
  "metadata": {}
}